zga/__init__.py
zga/assemblers.py
zga/essential.py
zga/preprocessing.py
zga/zga.py
zga/data/phiX174.fasta
zga/data/sr.adapters.fasta
zga-0.1.1.dist-info/LICENSE
zga-0.1.1.dist-info/METADATA
zga-0.1.1.dist-info/WHEEL
zga-0.1.1.dist-info/entry_points.txt
zga-0.1.1.dist-info/top_level.txt
zga-0.1.1.dist-info/RECORD
