Metadata-Version: 2.1
Name: zga
Version: 0.1.1
Summary: Prokaryotic genome assembly and annotation pipeline
Author-email: Aleksei Korzhenkov  <oscypek@ya.ru>
License: Copyright (c) 2020, Aleksei Korzhenkov All rights reserved.
Project-URL: Homepage, https://github.com/laxeye/zga/
Classifier: Programming Language :: Python :: 3
Classifier: Development Status :: 4 - Beta
Classifier: Environment :: Console
Classifier: Intended Audience :: Science/Research
Classifier: License :: OSI Approved :: BSD License
Classifier: Operating System :: POSIX :: Linux
Classifier: Topic :: Scientific/Engineering :: Bio-Informatics
Requires-Python: >=3.8
License-File: LICENSE
Requires-Dist: biopython
